pyc2e/__init__.py
pyc2e/__main__.py
pyc2e/common.py
pyc2e/interfaces/__init__.py
pyc2e/interfaces/response.py
pyc2e/interfaces/unix/__init__.py
pyc2e/interfaces/win32/__init__.py
pyc2e/interfaces/win32/win32api/__init__.py
pyc2e/interfaces/win32/win32api/common.py
pyc2e/interfaces/win32/win32api/events.py
pyc2e/interfaces/win32/win32api/mutex.py
pyc2e/interfaces/win32/win32api/process.py
pyc2e/interfaces/win32/win32api/wait.py
pyc2e-0.0.4.dist-info/METADATA
pyc2e-0.0.4.dist-info/WHEEL
pyc2e-0.0.4.dist-info/entry_points.txt
pyc2e-0.0.4.dist-info/top_level.txt
pyc2e-0.0.4.dist-info/RECORD
