Metadata-Version: 2.1
Name: pyc2e
Version: 0.0.4
Summary: Engine management & script injection for the Creatures Evolution Engine
Home-page: https://github.com/pushfoo/pyc2e
Author: pushfoo
Author-email: pushfoo@gmail.com
License: To be determined
Keywords: modding,tools,creatures,script injection,caos
Platform: UNKNOWN
Classifier: Development Status :: 3 - Alpha
Classifier: Environment :: Win32 (MS Windows)
Classifier: Intended Audience :: Developers
Classifier: Natural Language :: English
Classifier: Operating System :: Microsoft :: Windows
Classifier: Programming Language :: Python :: 3.7
Classifier: Topic :: Games/Entertainment :: Simulation
Classifier: Topic :: Software Development
Classifier: Topic :: Software Development :: Libraries
Classifier: Topic :: Software Development :: Testing
Classifier: Topic :: Utilities
Requires-Python: >=3.7
